basic_circuit/basic_Circuit.v
// Title: basic_Circuit.v
// Author: Wilmer Silva
// Last Modified: 11/23/2019
// Purpose: A basic combinational circuit is created as function F.
//          This code confirms that the equation was generated correctly,
//			    and gives a truth table used for debugging.

//***********************************************************************************
module basic_Circuit (
input A, B, C, D,	// inputs for combinational circuit
output F	        // output that represents the function F
);

wire A,B,C,D; // need to declare wires for each input, output, & internal signal
wire nB, nC, A_nC_nD, A_nB, B_D;
wire F;

// Instantiate gates in for an "architectural" solution
or (A_nC_nD,A,nC,nD);    // the leftmost variable is output...
or (A_nB,A,nB);          // all other variables are inputs...
or (B_D,B,D);
// F = (A+B')*(B+D)*(A+C'+D')
and (F,A_nC_nD,A_nB,B_D);
not (nA, A);
not (nB,B);
not (nC,C);
// Note that order doesn't matter here. These lines describe a
// physical arrangement, not an ordered list of operations.
endmodule
//***********************************************************************************

module basic_Circuit_tb;  // Note, no interface to test benches
 reg wA,wB,wC,wD;         // signals to be commanded by assignment statements must be "reg"
 wire wF;			            // output from unit-under-test is "wire"


initial begin       // This will allow us to graph the output
    $dumpfile ("basic_Circuit.vcd");
	  $dumpvars;
end

initial begin // within an “initial” block, code executes sequentially ONCE
	// $display acts like a common printf
	$display("  A B C D | nB nC A+nC+nD A+nB B+D  | F");
	$display(" ---------+-------------------------+---");
	// $monitor is like printf, AND, whenever one of the listed
	// variables changes again, it re-executes automatically
  // thus, creating a truth table to confirm output of circuit
  $monitor("  %b %b %b %b | %2b %2b   %2b    %2b   %2b   | %b",wA, wB, wC, wD, uut.nB, uut.nC, uut.A_nC_nD, uut.A_nB, uut.B_D, wF);
	wA = 0; wB = 0; wC = 0; wD = 0; #1;
	wA = 0; wB = 0; wC = 0; wD = 1; #1;
	wA = 0; wB = 0; wC = 1; wD = 0; #1;
	wA = 0; wB = 0; wC = 1; wD = 1; #1;
	wA = 0; wB = 1; wC = 0; wD = 0; #1;
	wA = 0; wB = 1; wC = 0; wD = 1; #1;
	wA = 0; wB = 1; wC = 1; wD = 0; #1;
	wA = 0; wB = 1; wC = 1; wD = 1; #1;
	wA = 1; wB = 0; wC = 0; wD = 0; #1;
	wA = 1; wB = 0; wC = 0; wD = 1; #1;
	wA = 1; wB = 0; wC = 1; wD = 0; #1;
	wA = 1; wB = 0; wC = 1; wD = 1; #1;
	wA = 1; wB = 1; wC = 0; wD = 0; #1;
	wA = 1; wB = 1; wC = 0; wD = 1; #1;
	wA = 1; wB = 1; wC = 1; wD = 0; #1;
	wA = 1; wB = 1; wC = 1; wD = 1; #1;
	$finish; // tells simulator to stop and return to the command prompt

end

// Connect UUT to test bench signals
basic_Circuit uut(
.A	(wA),
.B	(wB),
.C	(wC),
.D	(wD),
.F	(wF)
);
endmodule

basic_Circuit.vcd
$date
	Sun Nov 24 11:35:03 2019
$end
$version
	Icarus Verilog
$end
$timescale
	1s
$end
$scope module basic_Circuit_tb $end
$var wire 1 ! wF $end
$var reg 1 " wA $end
$var reg 1 # wB $end
$var reg 1 $ wC $end
$var reg 1 % wD $end
$scope module uut $end
$var wire 1 & A $end
$var wire 1 ' A_nB $end
$var wire 1 ( A_nC_nD $end
$var wire 1 ) B $end
$var wire 1 * B_D $end
$var wire 1 + C $end
$var wire 1 , D $end
$var wire 1 ! F $end
$var wire 1 - nA $end
$var wire 1 . nB $end
$var wire 1 / nC $end
$var wire 1 0 nD $end
$upscope $end
$upscope $end
$enddefinitions $end
#0
$dumpvars
z0
1/
1.
1-
0,
0+
0*
0)
1(
1'
0&
0%
0$
0#
0"
0!
$end
#1
1!
1*
1%
1,
#2
0!
x(
0*
0/
0%
0,
1$
1+
#3
x!
1*
1%
1,
#4
0!
1(
0'
1/
0.
0%
0,
0$
0+
1#
1)
#5
1%
1,
#6
x(
0/
0%
0,
1$
1+
#7
1%
1,
#8
1/
0*
1.
1(
1'
0-
0%
0,
0$
0+
0#
0)
1"
1&
#9
1!
1*
1%
1,
#10
0!
0*
0/
0%
0,
1$
1+
#11
1!
1*
1%
1,
#12
1/
0.
0%
0,
0$
0+
1#
1)
#13
1%
1,
#14
0/
0%
0,
1$
1+
#15
1%
1,
